{
    "id": "efa2733b-9c16-46c0-87bf-350203fb756c",
    "relatedPaper": 0,
    "context": {
        "metadata": {
            "titleEn": "Heat wave exposure data set of 34 key nodes in Pan-Third Pole (2015)",
            "description": "Based on 2015 as the base year, this data set selects population density, distribution of high-risk population and GDP as the evaluation indicators to complete the assessment of high temperature heat wave exposure at 34 key nodes. Exposure refers to the degree that a certain area may be affected by the disaster when the disaster occurs. In the extreme high temperature, human and economy are the two most obvious factors affected by the high temperature heat wave. The high-risk population is defined as children younger than five years old and the elderly older than 65 years old respectively. Equal weight overlapping plus method is adopted in the assessment. In order to eliminate the influence of unit difference, the data of each indicator layer is normalized before the assessment. The spatial resolution of the assessment result is 100m, covering 34 key nodes of the third pole.",
            "instructions": "File name: data is stored in TIF, grid form. The file name is \"country + exposure. TIF\", for example: Vientiane exposure. TIF, which represents the exposure grid data of Vientiane.\nData reading method: ArcGIS, ENVI and other software can be used to open the view and analysis.",
            "east": -165.0,
            "west": 12.0,
            "south": -12.0,
            "north": 85.0,
            "startTime": "2015-01-13 00:00:00",
            "endTime": "2016-01-12 00:00:00",
            "fileSize": 2391166442.0,
            "cstr": "18406.11.Meteoro.tpdc.270405",
            "doi": "10.11888/Meteoro.tpdc.270405",
            "dataFormat": null,
            "license": "Attribution-NonCommercial-ShareAlike 4.0 International (CC BY-NC-SA 4.0)"
        },
        "authorList": [
            {
                "nameEn": "GE Yong",
                "unitEn": "Institute of Geographic Sciences and Natural Resources Research, CAS"
            },
            {
                "nameEn": "YANG Fei",
                "unitEn": "Institute of Geographical Sciences and Natural Resource Research, CAS"
            },
            {
                "nameEn": "LIU Qingsheng",
                "unitEn": "Institute of Geographical Sciences and Natural Resource Research, CAS"
            }
        ],
        "literatureList": [
            {
                "titleEn": "Fine resolution mapping of population age-structures for health and development applications",
                "referenceEn": "Alegana V A , Atkinson P M , Pezzulo C , et al. (2015). Fine resolution mapping of population age-structures for health and development applications. Journal of The Royal Society Interface, 12(105), 20150073-20150073."
            }
        ],
        "keywordStandList": [
            {
                "nameEn": "Atmosphere"
            }
        ],
        "themeList": [
            {
                "nameEn": "Atmosphere Remote Sensing"
            },
            {
                "nameEn": "Atmospheric remote sensing products"
            }
        ],
        "placeKeywordList": [
            {
                "keywordEn": "Pan-Third Pole"
            }
        ],
        "temporalKeywordList": [
            {
                "keywordEn": "2015",
                "type": "temporal"
            }
        ],
        "fundVOList": null,
        "projectList": [
            {
                "titleEn": "National Tibetan Plateau / Third Pole Environment Data Center"
            }
        ],
        "relatedDataList": [
            {
                "titleEn": "Qilian Mountains integrated observatory network: Dataset of Heihe integrated observatory network (eddy covariance system of Huazhaizi station, 2018)"
            },
            {
                "titleEn": "Qilian Mountains integrated observatory network: Dataset of Heihe integrated observatory network (an observation system of meteorological elements gradient of Sidaoqiao superstation, 2018)"
            },
            {
                "titleEn": "Qilian Mountains integrated observatory network: Dataset of the Heihe River Basin integrated observatory network (automatic weather station of Jingyangling station, 2018)"
            },
            {
                "titleEn": "Qilian Mountains integrated observatory network: Dataset of Heihe integrated observatory network (automatic weather station of desert station, 2018)"
            },
            {
                "titleEn": "Qilian Mountains integrated observatory network: Dataset of Qinghai Lake integrated observatory network (eddy covariance system of Alpine meadow and grassland ecosystem Superstation, 2018)"
            },
            {
                "titleEn": "Qilian Mountains integrated observatory network: Dataset of the Heihe River Basin integrated observatory network (automatic weather station of Heihe remote sensing station, 2018)"
            },
            {
                "titleEn": "Qilian Mountains integrated observatory network: Dataset of Heihe integrated observatory network (large aperture scintillometer of Daman Superstation, 2018)"
            },
            {
                "titleEn": "Qilian Mountains integrated observatory network: Dataset of Heihe integrated observatory network (eddy covariance system of Daman Superstation, 2018)"
            },
            {
                "titleEn": "Qilian Mountains integrated observatory network: Dataset of Heihe integrated observatory network (eddy covariance system of Zhangye wetland station, 2018)"
            },
            {
                "titleEn": "Qilian Mountains integrated observatory network: Dataset of Heihe integrated observatory network (eddy covariance system of desert station, 2018)"
            }
        ]
    },
    "extract_pdfs_data": [],
    "query": [
        {
            "Feature Specification": [
                {
                    "Question": "What are the defining characteristics used for evaluating high-temperature heatwave exposure at key nodes in the Pan-Third Pole region?",
                    "Answer": "population density, distribution of high-risk populations, GDP, children under the age of five, elderly people over the age of 65, equal-weight overlay method, data normalization, spatial resolution of 100 meters, 34 key node areas",
                    "Level": "C5(Evaluating)"
                }
            ]
        },
        {
            "Quantification": [
                {
                    "Question": "What is the spatial resolution of the data used to evaluate high-temperature heatwave exposure across the 34 key nodes in the Pan-Third Pole region?",
                    "Answer": "100 meters",
                    "Level": "C1(Remembering)"
                }
            ]
        },
        {
            "Definition": [
                {
                    "Question": "What does 'exposure assessment' mean in the context of evaluating high-temperature heatwave impacts in key regions?",
                    "Answer": "In this context, 'exposure assessment' refers to evaluating the degree to which a region may be affected by a disaster, such as extreme high temperatures. It involves using indicators like population density, high-risk population distribution, and GDP to assess exposure levels. High-risk populations are defined as children under five and adults over 65. The assessment method includes normalizing data to eliminate unit differences and applying equal weight overlay techniques, with results having a spatial resolution of 100 meters covering key areas.",
                    "Level": "C2(Understanding)"
                }
            ]
        },
        {
            "Comparison": [
                {
                    "Question": "How do the methods for assessing high-temperature heatwave exposure using population density, high-risk population distribution, and GDP as indicators compare to other potential data collection methods that might use different indicators or assessment strategies?",
                    "Answer": "The methods for assessing high-temperature heatwave exposure in the specified dataset use population density, high-risk population distribution, and GDP as core indicators, applying an equal-weight overlay method with normalization to eliminate unit differences. This approach provides a spatial resolution of 100m covering 34 key nodes in the region. These methods may differ from other data collection techniques that could utilize alternative indicators, such as health data, infrastructure resilience, or environmental factors, and might employ different weighting strategies or resolution scales to assess heatwave exposure.",
                    "Level": "C4(Analyzing)"
                }
            ]
        },
        {
            "Interpretation": [
                {
                    "Question": "How do the chosen indicators such as population density, distribution of vulnerable populations, and GDP contribute to understanding the exposure degree of key nodes to heatwaves, and what might this infer about the region's vulnerability and adaptive capacity?",
                    "Answer": "The indicators of population density, distribution of vulnerable populations, and GDP are crucial in assessing the exposure degree as they directly affect how heatwaves impact human health and economic activities. High population density can indicate more people at risk, while the distribution of vulnerable populations highlights the age groups most susceptible to heat-related health issues. GDP can reflect the region's economic resilience and resources available for adaptive measures. Together, these indicators can infer the region's overall vulnerability and capacity to adapt to extreme heat conditions.",
                    "Level": "C4(Analyzing)"
                }
            ]
        },
        {
            "Causal Consequence": [
                {
                    "Question": "What are the potential consequences of using population density, distribution of high-risk populations, and GDP as evaluation indicators on the assessment of heatwave exposure levels in key regions?",
                    "Answer": "Using population density, distribution of high-risk populations, and GDP as evaluation indicators allows for a comprehensive assessment of heatwave exposure levels by identifying areas where the impact on human and economic factors is most pronounced. This approach helps highlight regions with a higher likelihood of adverse effects during extreme heat events, particularly where vulnerable populations, such as children under five and elderly over 65, are concentrated. By normalizing these indicators and applying equal weighting, the assessment provides a balanced view of exposure, aiding in targeted disaster preparedness and response strategies.",
                    "Level": "C5(Evaluating)"
                }
            ]
        },
        {
            "Goal Orientation": [
                {
                    "Question": "Why is it important to evaluate the exposure to heatwaves at critical nodes using population density, high-risk population distribution, and GDP as indicators?",
                    "Answer": "Evaluating the exposure to heatwaves at critical nodes using population density, high-risk population distribution, and GDP as indicators is important because, during extreme heat events, humans and the economy are significantly affected. The assessment helps in understanding the potential impact of disasters on a region. By focusing on high-risk populations, such as children under five and adults over 65, the evaluation aims to identify vulnerable groups and regions, thereby aiding in better preparedness and mitigation strategies. The use of these specific indicators, with normalization and equal weighting, ensures a comprehensive analysis of exposure levels across the 34 critical nodes in the Pan-Third Pole area.",
                    "Level": "C5(Evaluating)"
                }
            ]
        },
        {
            "Instrumental/Procedural": [
                {
                    "Question": "What methodologies are used to assess exposure levels to high-temperature heatwaves in key regions, considering factors like population density, vulnerable population distribution, and GDP?",
                    "Answer": "The evaluation uses a method where population density, high-risk population distribution (defined as children under five and elderly over 65), and GDP are selected as assessment indicators. These indicators are integrated with equal weighting. To mitigate unit discrepancies, each dataset layer is normalized before assessment, and the spatial resolution of the evaluation results is 100 meters, covering 34 key nodes in the region.",
                    "Level": "C4(Analyzing)"
                }
            ]
        }
    ]
}